synthgauge/__init__.py
synthgauge/datasets.py
synthgauge/evaluator.py
synthgauge/plot.py
synthgauge/utils.py
synthgauge/metrics/__init__.py
synthgauge/metrics/classification.py
synthgauge/metrics/cluster.py
synthgauge/metrics/correlation.py
synthgauge/metrics/density.py
synthgauge/metrics/nist.py
synthgauge/metrics/privacy.py
synthgauge/metrics/propensity.py
synthgauge/metrics/univariate.py
synthgauge-2.2.0.dist-info/LICENSE
synthgauge-2.2.0.dist-info/METADATA
synthgauge-2.2.0.dist-info/WHEEL
synthgauge-2.2.0.dist-info/top_level.txt
synthgauge-2.2.0.dist-info/RECORD
