Metadata-Version: 2.1
Name: synthgauge
Version: 2.2.0
Summary: A package for evaluating synthetic data
Home-page: https://github.com/datasciencecampus/synthgauge
Author: Office For National Statistics Data Science Campus
Author-email: datacampus@ons.gov.uk
Project-URL: Documentation, https://datasciencecampus.github.io/synthgauge
Project-URL: Bug Tracker, https://github.com/datasciencecampus/synthgauge/issues
Classifier: Programming Language :: Python :: 3
Classifier: License :: OSI Approved :: MIT License
Classifier: Operating System :: OS Independent
Classifier: Intended Audience :: Science/Research
Classifier: Topic :: Scientific/Engineering :: Information Analysis
Requires-Python: >=3.6
License-File: LICENSE
Requires-Dist: kmodes (>=0.11.1)
Requires-Dist: matplotlib (>=3.3.2)
Requires-Dist: numpy (>=1.19.2)
Requires-Dist: scikit-learn (>=0.24.0)
Requires-Dist: pandas (>=1.1.3)
Requires-Dist: scipy (>=1.5.2)
Requires-Dist: seaborn (<0.12.0,>=0.11.0)
Provides-Extra: dev
Requires-Dist: black (>=22.3.0) ; extra == 'dev'
Requires-Dist: flake8 (>=4.0.1) ; extra == 'dev'
Requires-Dist: interrogate (>=1.5.0) ; extra == 'dev'
Requires-Dist: isort (>=5.10.1) ; extra == 'dev'
Requires-Dist: pre-commit (>=2.17.0) ; extra == 'dev'
Requires-Dist: synthgauge[docs] ; extra == 'dev'
Requires-Dist: synthgauge[test] ; extra == 'dev'
Provides-Extra: docs
Requires-Dist: nbsphinx-link (==1.3.0) ; extra == 'docs'
Requires-Dist: sphinx (==4.3.2) ; extra == 'docs'
Requires-Dist: sphinx-autoapi (==1.8.4) ; extra == 'docs'
Requires-Dist: sphinx-rtd-theme (==1.0.0) ; extra == 'docs'
Requires-Dist: ipython (==7.16.3) ; (python_version < "3.7") and extra == 'docs'
Requires-Dist: nbsphinx (==0.8.8) ; (python_version < "3.7") and extra == 'docs'
Requires-Dist: ipython (==7.17.0) ; (python_version > "3.6") and extra == 'docs'
Requires-Dist: nbsphinx (==0.8.9) ; (python_version > "3.6") and extra == 'docs'
Provides-Extra: test
Requires-Dist: pytest (>=6.2.5) ; extra == 'test'
Requires-Dist: pytest-cov (==3.0.0) ; extra == 'test'
Requires-Dist: hypothesis (==6.31.6) ; (python_version < "3.7") and extra == 'test'
Requires-Dist: pytest-randomly (==3.10.3) ; (python_version < "3.7") and extra == 'test'
Requires-Dist: hypothesis (>=6.47.2) ; (python_version > "3.6") and extra == 'test'
Requires-Dist: pytest-randomly (==3.12.0) ; (python_version > "3.6") and extra == 'test'
